.gitmodules
CMakeLists.txt
LICENSE
MANIFEST.in
README.md
requirements.txt
setup.py
tox.ini
lib/DronePoseLib/.travis.yml
lib/DronePoseLib/CMakeLists.txt
lib/DronePoseLib/LICENSE
lib/DronePoseLib/README.md
lib/DronePoseLib/build.sh
lib/DronePoseLib/example.cpp
lib/DronePoseLib/cmake_modules/CodeCoverage.cmake
lib/DronePoseLib/includes/DronePoseLib/get_valtonenornhag_arxiv_2021.hpp
lib/DronePoseLib/includes/DronePoseLib/relpose.hpp
lib/DronePoseLib/matlab/compile_mex.m
lib/DronePoseLib/matlab/test_noise_sensitivity_realistic.m
lib/DronePoseLib/matlab/test_numerical_stability_our_fEf_no_rot_3pt.m
lib/DronePoseLib/matlab/test_numerical_stability_our_frEfr_no_rot_4pt.m
lib/DronePoseLib/matlab/test_numerical_stability_our_rEr_no_rot_3pt.m
lib/DronePoseLib/matlab/helpers/compare_to_gt.m
lib/DronePoseLib/matlab/helpers/generate_points_realistic.m
lib/DronePoseLib/matlab/helpers/normalise2dpts.m
lib/DronePoseLib/matlab/helpers/pflat.m
lib/DronePoseLib/matlab/helpers/radialdistort.m
lib/DronePoseLib/matlab/helpers/radialundistort.m
lib/DronePoseLib/matlab/helpers/rotm.m
lib/DronePoseLib/matlab/helpers/skew.m
lib/DronePoseLib/matlab/src/get_valtonenornhag_arxiv_2021_fEf_mex.cpp
lib/DronePoseLib/matlab/src/get_valtonenornhag_arxiv_2021_frEfr_mex.cpp
lib/DronePoseLib/matlab/src/get_valtonenornhag_arxiv_2021_rEr_mex.cpp
lib/DronePoseLib/src/helpers/charpoly.h
lib/DronePoseLib/src/helpers/normalize2dpts.cpp
lib/DronePoseLib/src/helpers/normalize2dpts.hpp
lib/DronePoseLib/src/helpers/quartic.cpp
lib/DronePoseLib/src/helpers/quartic.hpp
lib/DronePoseLib/src/helpers/radial.cpp
lib/DronePoseLib/src/helpers/radial.hpp
lib/DronePoseLib/src/helpers/sturm.h
lib/DronePoseLib/src/solvers/valtonenornhag_arxiv_2021/fEf/get_fEf.cpp
lib/DronePoseLib/src/solvers/valtonenornhag_arxiv_2021/frEfr/coeffs_frEfr.cpp
lib/DronePoseLib/src/solvers/valtonenornhag_arxiv_2021/frEfr/coeffs_frEfr.hpp
lib/DronePoseLib/src/solvers/valtonenornhag_arxiv_2021/frEfr/get_frEfr.cpp
src/droneposelib.egg-info/PKG-INFO
src/droneposelib.egg-info/SOURCES.txt
src/droneposelib.egg-info/dependency_links.txt
src/droneposelib.egg-info/not-zip-safe
src/droneposelib.egg-info/requires.txt
src/droneposelib.egg-info/top_level.txt
