Metadata-Version: 2.1
Name: droneposelib
Version: 0.0.0a4
Summary: A Python package for Visual-Inertial Odometry
Home-page: https://github.com/marcusvaltonen/python-droneposelib
Author: Marcus Valtonen Ornhag
Author-email: marcusvaltonen@gmail.com
License: MIT
Keywords: computer vision visual-inertial odometry IMU UAV
Platform: UNKNOWN
Classifier: Development Status :: 1 - Planning
Classifier: License :: OSI Approved :: MIT License
Classifier: Intended Audience :: Developers
Classifier: Intended Audience :: Science/Research
Classifier: Programming Language :: Python :: 3
Classifier: Programming Language :: Python :: 3.6
Classifier: Programming Language :: Python :: 3.7
Classifier: Programming Language :: Python :: 3.8
Classifier: Operating System :: POSIX :: Linux
Classifier: Topic :: Scientific/Engineering
Classifier: Topic :: Scientific/Engineering :: Image Processing
Requires-Python: >=3
Provides-Extra: dev
